{
  "exported_at": "20250913-230320",
  "pipeline": "bow_title+text_nb",
  "rep": "BoW",
  "input": "Title+Text (concatenated string, space-separated tokens in Text)",
  "vectorizer": {
    "type": "CountVectorizer",
    "fixed_vocabulary": true,
    "vocab_size": 6548,
    "vocab_md5": "b05ed0c0072bd94f182942b4911686ff"
  },
  "classifier": "MultinomialNB",
  "target": {
    "name": "Recommended IND",
    "classes": [
      0,
      1
    ]
  },
  "expects": {
    "title": "raw string (may be empty)",
    "processed_text_tokens": "string of space-separated tokens (from Task 1 preprocessing)",
    "combined_rule": "combined_text = tokenize(title).join(' ') + ' ' + processed_text_tokens"
  },
  "files_required_in_webapp": [
    "this .joblib file only (CountVectorizer is embedded with fixed vocab)"
  ],
  "notes": "Ensure the same Task-1 preprocessing/tokenization is used to generate processed_text_tokens."
}